tikray/__init__.py
tikray/cli.py
tikray/core.py
tikray/function.jq
tikray/function.py
tikray/model/__init__.py
tikray/model/base.py
tikray/model/bucket.py
tikray/model/collection.py
tikray/model/fluent.py
tikray/model/moksha.py
tikray/model/project.py
tikray/model/treatment.py
tikray/util/__init__.py
tikray/util/data.py
tikray/util/dictx.py
tikray/util/expression.py
tikray/util/locator.py
tikray/util/logging.py
tikray/util/rson.py
tikray-0.3.1.dist-info/licenses/LICENSE
tikray-0.3.1.dist-info/METADATA
tikray-0.3.1.dist-info/WHEEL
tikray-0.3.1.dist-info/entry_points.txt
tikray-0.3.1.dist-info/top_level.txt
tikray-0.3.1.dist-info/RECORD
