Metadata-Version: 2.4
Name: tikray
Version: 0.3.1
Summary: A compact data transformation engine.
Author-email: Andreas Motl <andreas.motl@panodata.org>
License-Expression: MIT
Project-URL: Changelog, https://tikray.readthedocs.io/changes.html
Project-URL: Documentation, https://tikray.readthedocs.io/
Project-URL: Homepage, https://tikray.readthedocs.io/
Project-URL: Issues, https://github.com/panodata/tikray/issues
Project-URL: Repository, https://github.com/panodata/tikray
Keywords: conversion,convert,data,decode,deserialize,encode,i/o,jmespath,json,jsonpointer,map data,marshal,nested data,serialize,sql,tool,transcode,transform,translate,transon,unmarshal,unserialize,utility
Classifier: Development Status :: 4 - Beta
Classifier: Environment :: Plugins
Classifier: Intended Audience :: Developers
Classifier: Intended Audience :: Education
Classifier: Intended Audience :: Information Technology
Classifier: Intended Audience :: Manufacturing
Classifier: Intended Audience :: Science/Research
Classifier: Intended Audience :: System Administrators
Classifier: Intended Audience :: Telecommunications Industry
Classifier: Operating System :: OS Independent
Classifier: Operating System :: POSIX :: Linux
Classifier: Operating System :: Unix
Classifier: Programming Language :: Python
Classifier: Programming Language :: Python :: 3 :: Only
Classifier: Programming Language :: Python :: 3.9
Classifier: Programming Language :: Python :: 3.10
Classifier: Programming Language :: Python :: 3.11
Classifier: Programming Language :: Python :: 3.12
Classifier: Programming Language :: Python :: 3.13
Classifier: Programming Language :: Python :: 3.14
Classifier: Programming Language :: Python :: Implementation :: CPython
Classifier: Programming Language :: Python :: Implementation :: PyPy
Classifier: Programming Language :: SQL
Classifier: Topic :: Adaptive Technologies
Classifier: Topic :: Communications
Classifier: Topic :: Database
Classifier: Topic :: Documentation
Classifier: Topic :: Education
Classifier: Topic :: Internet
Classifier: Topic :: Office/Business
Classifier: Topic :: Scientific/Engineering
Classifier: Topic :: Scientific/Engineering :: Information Analysis
Classifier: Topic :: Scientific/Engineering :: Interface Engine/Protocol Translator
Classifier: Topic :: Software Development :: Libraries
Classifier: Topic :: Software Development :: Pre-processors
Classifier: Topic :: Software Development :: Testing
Classifier: Topic :: Software Development :: Version Control
Classifier: Topic :: System :: Archiving
Classifier: Topic :: System :: Benchmark
Classifier: Topic :: System :: Clustering
Classifier: Topic :: System :: Distributed Computing
Classifier: Topic :: System :: Logging
Classifier: Topic :: System :: Monitoring
Classifier: Topic :: System :: Networking
Classifier: Topic :: System :: Systems Administration
Classifier: Topic :: Text Processing
Classifier: Topic :: Utilities
Requires-Python: >=3.9
License-File: LICENSE
Requires-Dist: cattrs<26
Requires-Dist: click<9
Requires-Dist: importlib-resources<6.5; python_version < "3.10"
Requires-Dist: jmespath<1.1
Requires-Dist: jq<1.11
Requires-Dist: jsonpointer<4
Requires-Dist: orjson<4
Requires-Dist: orjsonl<2
Requires-Dist: python-dateutil<2.10
Requires-Dist: pyyaml<7
Requires-Dist: rsonpy<0.2
Requires-Dist: toolz<2
Requires-Dist: tqdm<5
Requires-Dist: transon==0.0.7
Provides-Extra: develop
Requires-Dist: mypy<1.20; extra == "develop"
Requires-Dist: poethepoet<1; extra == "develop"
Requires-Dist: pyproject-fmt<3; extra == "develop"
Requires-Dist: ruff<0.15; extra == "develop"
Requires-Dist: validate-pyproject<1,>=0.23; extra == "develop"
Provides-Extra: docs
Requires-Dist: furo>=2025; extra == "docs"
Requires-Dist: myst-parser[linkify]<4,>=0.18; extra == "docs"
Requires-Dist: sphinx-autobuild>=2024; extra == "docs"
Requires-Dist: sphinx-copybutton; extra == "docs"
Requires-Dist: sphinx-design-elements<1; extra == "docs"
Requires-Dist: sphinxcontrib-mermaid<2; extra == "docs"
Requires-Dist: sphinxext-opengraph<1; extra == "docs"
Provides-Extra: mongodb
Requires-Dist: pymongo<4.16; extra == "mongodb"
Provides-Extra: release
Requires-Dist: build<2; extra == "release"
Requires-Dist: twine<7; extra == "release"
Provides-Extra: test
Requires-Dist: pytest<9; extra == "test"
Requires-Dist: pytest-cov<8; extra == "test"
Requires-Dist: pytest-mock<4; extra == "test"
Dynamic: license-file
